formation/__init__.py
formation/__version__.py
formation/for_requests.py
formation/formation.py
formation/middleware/__init__.py
formation/middleware/accept.py
formation/middleware/breaker.py
formation/middleware/context.py
formation/middleware/context_logger.py
formation/middleware/logger.py
formation/middleware/request_duration.py
formation/middleware/request_id.py
formation/middleware/retry.py
formation/middleware/timeout.py
formation/middleware/ua.py
formation-0.1.37.dist-info/LICENSE.txt
formation-0.1.37.dist-info/WHEEL
formation-0.1.37.dist-info/METADATA
formation-0.1.37.dist-info/RECORD
