Metadata-Version: 2.1
Name: formation
Version: 0.1.37
Summary: A generic functional middleware infrastructure for Python.
Home-page: https://github.com/jondot/formation
License: MIT
Keywords: flask,django,requests,middleware,functional
Author: Dotan Nahum
Author-email: jondotan@gmail.com
Requires-Python: >=2.7, !=3.0.*, !=3.1.*, !=3.2.*, !=3.3.*, !=3.4.*, !=3.5.*, !=3.6.*
Classifier: License :: OSI Approved :: MIT License
Classifier: Programming Language :: Python :: 2
Classifier: Programming Language :: Python :: 3
Classifier: Programming Language :: Python :: 3.7
Classifier: Programming Language :: Python :: 3.8
Provides-Extra: lint
Requires-Dist: attrs (>=19.1,<20.0)
Requires-Dist: attrs-serde (>=0.2.2,<0.3.0)
Requires-Dist: cytoolz (>=0.9.0,<0.10.0)
Requires-Dist: lxml (>=4.2,<5.0)
Requires-Dist: pybreaker (>=0.4.5,<0.5.0)
Requires-Dist: requests (>=2.20,<3.0)
Requires-Dist: toolz (>=0.9.0,<0.10.0)
Requires-Dist: xmltodict (>=0.11.0,<0.12.0)
Project-URL: Documentation, https://github.com/jondot/formation
Project-URL: Repository, https://github.com/jondot/formation
